python_cpdlc/__init__.py
python_cpdlc/acars_message.py
python_cpdlc/acars_message.pyi
python_cpdlc/acars_message_factory.py
python_cpdlc/acars_message_factory.pyi
python_cpdlc/cpdlc.py
python_cpdlc/cpdlc.pyi
python_cpdlc/cpdlc_message.py
python_cpdlc/cpdlc_message.pyi
python_cpdlc/cpdlc_message_id.py
python_cpdlc/cpdlc_message_id.pyi
python_cpdlc/enums.py
python_cpdlc/enums.pyi
python_cpdlc/exception.py
python_cpdlc/exception.pyi
python_cpdlc/poller.py
python_cpdlc/poller.pyi
python_cpdlc-1.3.8.dist-info/licenses/LICENSE
python_cpdlc-1.3.8.dist-info/METADATA
python_cpdlc-1.3.8.dist-info/WHEEL
python_cpdlc-1.3.8.dist-info/top_level.txt
python_cpdlc-1.3.8.dist-info/RECORD
