Metadata-Version: 2.4
Name: python-cpdlc
Version: 1.3.8
Summary: A simple CPDLC client
Author-email: Half_nothing <Half_nothing@163.com>
License: GPL-3.0-or-later
Keywords: CPDLC,python,httpx
Classifier: License :: OSI Approved :: GNU General Public License v3 or later (GPLv3+)
Classifier: Programming Language :: Python :: 3
Classifier: Programming Language :: Python :: 3.12
Classifier: Environment :: Console
Classifier: Intended Audience :: Developers
Classifier: Natural Language :: Chinese (Simplified)
Classifier: Natural Language :: English
Requires-Python: >=3.12
License-File: LICENSE
Requires-Dist: loguru>=0.7.3
Requires-Dist: beautifulsoup4>=4.13.4
Requires-Dist: lxml>=5.4.0
Requires-Dist: httpx>=0.28.1
Provides-Extra: dev
Requires-Dist: mypy>=1.17.0; extra == "dev"
Dynamic: license-file
